voltree/__init__.py
voltree/cli.py
voltree-0.1.0.dist-info/licenses/LICENSE
voltree-0.1.0.dist-info/METADATA
voltree-0.1.0.dist-info/WHEEL
voltree-0.1.0.dist-info/entry_points.txt
voltree-0.1.0.dist-info/top_level.txt
voltree-0.1.0.dist-info/RECORD
